rustc_dev_t_x64_win_msvc_nightly_p5/__init__.py
rustc_dev_t_x64_win_msvc_nightly_p5/data/derive_setters-a04de28c3cc0378a.pdb
rustc_dev_t_x64_win_msvc_nightly_p5/data/derive_where-06dd06218cd036c9.dll
rustc_dev_t_x64_win_msvc_nightly_p5/data/icu_provider_macros-d4f887cd84c98d98.dll.lib
rustc_dev_t_x64_win_msvc_nightly_p5/data/libadler2-54d5f37c9893c3ee.rmeta
rustc_dev_t_x64_win_msvc_nightly_p5/data/libblock_buffer-e7b0bb58135c26f9.rmeta
rustc_dev_t_x64_win_msvc_nightly_p5/data/libcrypto_common-aae56d7051d62adc.rmeta
rustc_dev_t_x64_win_msvc_nightly_p5/data/libicu_locid_transform-ff0e38d360c47b53.rmeta
rustc_dev_t_x64_win_msvc_nightly_p5/data/libicu_provider_adapters-48a05563766f5d33.rmeta
rustc_dev_t_x64_win_msvc_nightly_p5/data/libitoa-0e0e1541b02a271d.rmeta
rustc_dev_t_x64_win_msvc_nightly_p5/data/libnu_ansi_term-32db0deaaad408e5.rmeta
rustc_dev_t_x64_win_msvc_nightly_p5/data/libparking_lot-21092a02af6971d3.rmeta
rustc_dev_t_x64_win_msvc_nightly_p5/data/librustc_abi-31c22deec5264f76.rmeta
rustc_dev_t_x64_win_msvc_nightly_p5/data/librustc_ast_pretty-0488aee23933b63a.rmeta
rustc_dev_t_x64_win_msvc_nightly_p5/data/librustc_hashes-004a8b2a398e9eb8.rmeta
rustc_dev_t_x64_win_msvc_nightly_p5/data/librustc_hir_pretty-a40e627c7a517dee.rmeta
rustc_dev_t_x64_win_msvc_nightly_p5/data/librustc_incremental-5cc8d740d9f1c435.rmeta
rustc_dev_t_x64_win_msvc_nightly_p5/data/librustc_infer-9378a80a44fe209b.rmeta
rustc_dev_t_x64_win_msvc_nightly_p5/data/librustc_llvm-0e4a9c076f7e749d.rmeta
rustc_dev_t_x64_win_msvc_nightly_p5/data/librustc_mir_transform-0e1b813c98f6fdea.rmeta
rustc_dev_t_x64_win_msvc_nightly_p5/data/librustc_target-999b8db0d6f6cfc4.rmeta
rustc_dev_t_x64_win_msvc_nightly_p5/data/librustc_ty_utils-87113cbd40f21206.rmeta
rustc_dev_t_x64_win_msvc_nightly_p5/data/libryu-700b6eb3f91445d0.rmeta
rustc_dev_t_x64_win_msvc_nightly_p5/data/libscopeguard-c3fde32b39adfbb3.rmeta
rustc_dev_t_x64_win_msvc_nightly_p5/data/libself_cell-f7a8afe2e0807cca.rmeta
rustc_dev_t_x64_win_msvc_nightly_p5-1.91.0.dist-info/METADATA
rustc_dev_t_x64_win_msvc_nightly_p5-1.91.0.dist-info/WHEEL
rustc_dev_t_x64_win_msvc_nightly_p5-1.91.0.dist-info/top_level.txt
rustc_dev_t_x64_win_msvc_nightly_p5-1.91.0.dist-info/RECORD
